README.rst
setup.py
dirg/__init__.py
dirg/_version.py
dirg/container_utils.py
dirg/dirg.py
dirg/service_utils.py
dirg.egg-info/PKG-INFO
dirg.egg-info/SOURCES.txt
dirg.egg-info/dependency_links.txt
dirg.egg-info/entry_points.txt
dirg.egg-info/requires.txt
dirg.egg-info/top_level.txt