Metadata-Version: 1.1
Name: dirg
Version: 1.0.0
Summary: A docker orchestration tool.
Home-page: https://github.com/smaato/dirg
Author: Stephan Brosinski
Author-email: stephan.brosinski@smaato.com
License: MIT License
Download-URL: https://github.com/smaato/dirg
Keywords: docker,orchestration,docker-py
Platform: UNKNOWN
Classifier: Programming Language :: Python :: 2.7
Classifier: Development Status :: 3 - Alpha
Classifier: License :: OSI Approved :: MIT License
Classifier: Natural Language :: English
Classifier: Environment :: Other Environment
Classifier: Intended Audience :: Developers
Classifier: Topic :: Software Development :: Build Tools
